revenuecat_sdk/__init__.py
revenuecat_sdk/client.py
revenuecat_sdk/enums.py
revenuecat_sdk/errors.py
revenuecat_sdk/response.py
revenuecat_sdk/utils.py
revenuecat_sdk-0.0.3.dist-info/LICENSE
revenuecat_sdk-0.0.3.dist-info/METADATA
revenuecat_sdk-0.0.3.dist-info/WHEEL
revenuecat_sdk-0.0.3.dist-info/top_level.txt
revenuecat_sdk-0.0.3.dist-info/RECORD
