Metadata-Version: 2.1
Name: revenuecat-sdk
Version: 0.0.3
Summary: A Python client library for the RevenueCat API
Home-page: https://github.com/ha3/revenuecat_sdk
Author: Hakan Özdemir
Author-email: hakanozdemir2@yandex.com
License: MIT
Project-URL: Bug Tracker, https://github.com/ha3/revenuecat_sdk/issues
Keywords: revenuecat
Platform: UNKNOWN
Classifier: Intended Audience :: Developers
Classifier: Topic :: Software Development :: Build Tools
Classifier: License :: OSI Approved :: MIT License
Classifier: Programming Language :: Python :: 3
Classifier: Programming Language :: Python :: 3.6
Classifier: Programming Language :: Python :: 3.7
Classifier: Programming Language :: Python :: 3.8
Classifier: Programming Language :: Python :: Implementation :: CPython
Classifier: Programming Language :: Python :: Implementation :: PyPy
Requires-Python: >=3.6
License-File: LICENSE
Requires-Dist: requests (>=2.0)
